[
  {
    "latitude": 36.802695,
    "longitude": -76.055211,
    "count": 1,
    "reasons": [
      "Vehicle Crash"
    ]
  },
  {
    "latitude": 38.765686,
    "longitude": -77.221351,
    "count": 5,
    "reasons": [
      "Disabled Vehicle",
      "Vehicle Crash"
    ]
  },
  {
    "latitude": 37.908916,
    "longitude": -76.671898,
    "count": 1,
    "reasons": [
      "Tractor Trailer Crash"
    ]
  },
  {
    "latitude": 38.656701,
    "longitude": -77.417648,
    "count": 3,
    "reasons": [
      "Other Traffic",
      "Disabled Tractor Trailer",
      "Disabled Vehicle"
    ]
  },
  {
    "latitude": 36.701403,
    "longitude": -78.398297,
    "count": 1,
    "reasons": [
      "Other Security/Police Activity"
    ]
  },
  {
    "latitude": 37.778255,
    "longitude": -77.192854,
    "count": 1,
    "reasons": [
      "Vehicle Crash"
    ]
  }
]