[
  {
    "latitude": 37.575135,
    "longitude": -79.812531,
    "count": 1,
    "reasons": [
      "Disabled Vehicle"
    ]
  },
  {
    "latitude": 39.222619,
    "longitude": -78.29897,
    "count": 2,
    "reasons": [
      "Other Traffic",
      "Disabled Vehicle"
    ]
  },
  {
    "latitude": 38.179497,
    "longitude": -77.661503,
    "count": 1,
    "reasons": [
      "Other Traffic"
    ]
  },
  {
    "latitude": 38.765686,
    "longitude": -77.221351,
    "count": 4,
    "reasons": [
      "Other Traffic",
      "Disabled Vehicle"
    ]
  },
  {
    "latitude": 36.768592,
    "longitude": -77.845384,
    "count": 1,
    "reasons": [
      "Disabled Vehicle"
    ]
  },
  {
    "latitude": 37.206904,
    "longitude": -77.391893,
    "count": 1,
    "reasons": [
      "Disabled Vehicle"
    ]
  },
  {
    "latitude": 36.690587,
    "longitude": -76.616102,
    "count": 1,
    "reasons": [
      "Bridge/Tunnel Stoppage"
    ]
  },
  {
    "latitude": 38.876507,
    "longitude": -77.099033,
    "count": 1,
    "reasons": [
      "Disabled Vehicle"
    ]
  }
]