[
  {
    "latitude": 38.765686,
    "longitude": -77.221351,
    "count": 1,
    "reasons": [
      "Disabled Vehicle"
    ]
  },
  {
    "latitude": 38.836826,
    "longitude": -77.856034,
    "count": 1,
    "reasons": [
      "Vehicle Crash"
    ]
  },
  {
    "latitude": 37.412079,
    "longitude": -77.630101,
    "count": 2,
    "reasons": [
      "Multi-Vehicle Crash",
      "Advisory"
    ]
  },
  {
    "latitude": 36.721982,
    "longitude": -80.733116,
    "count": 2,
    "reasons": [
      "Advisory"
    ]
  },
  {
    "latitude": 37.837635,
    "longitude": -77.625236,
    "count": 1,
    "reasons": [
      "Vehicle Crash"
    ]
  },
  {
    "latitude": 37.468543,
    "longitude": -77.31012,
    "count": 1,
    "reasons": [
      "Vehicle Crash"
    ]
  },
  {
    "latitude": 37.232258,
    "longitude": -79.073377,
    "count": 1,
    "reasons": [
      "Tractor Trailer Crash"
    ]
  }
]